depending/__init__.py
depending/variables.py
depending-0.1.7.dist-info/WHEEL
depending-0.1.7.dist-info/METADATA
depending-0.1.7.dist-info/RECORD
