Metadata-Version: 2.1
Name: depending
Version: 0.1.7
Summary: 
Author: Blake
Author-email: blakeinvictoria@gmail.com
Requires-Python: >=3.8,<4.0
Classifier: Programming Language :: Python :: 3
Classifier: Programming Language :: Python :: 3.8
Classifier: Programming Language :: Python :: 3.9
